lenscat/__init__.py
lenscat/_version.py
lenscat/catalog.py
lenscat/utils.py
lenscat/data/catalog.csv
lenscat-1.1.3.dist-info/licenses/LICENSE
lenscat-1.1.3.dist-info/METADATA
lenscat-1.1.3.dist-info/WHEEL
lenscat-1.1.3.dist-info/top_level.txt
lenscat-1.1.3.dist-info/RECORD
