Metadata-Version: 2.4
Name: lenscat
Version: 1.1.3
Summary: A public and community-maintained catalog of known strong gravitational lenses
Classifier: License :: OSI Approved :: MIT License
Requires-Python: >=3.9
License-File: LICENSE
Requires-Dist: astropy>=6.0.0
Requires-Dist: ligo.skymap
Requires-Dist: numpy
Requires-Dist: pandas
Dynamic: classifier
Dynamic: description
Dynamic: description-content-type
Dynamic: license-file
Dynamic: requires-dist
Dynamic: requires-python
Dynamic: summary
